llm_auto_web_tester/__init__.py
llm_auto_web_tester/llm_auto_web_tester.py
llm_auto_web_tester/mcp_server_utils.py
llm_auto_web_tester-0.1.4.dist-info/METADATA
llm_auto_web_tester-0.1.4.dist-info/WHEEL
llm_auto_web_tester-0.1.4.dist-info/entry_points.txt
llm_auto_web_tester-0.1.4.dist-info/top_level.txt
llm_auto_web_tester-0.1.4.dist-info/RECORD
