Metadata-Version: 2.2
Name: llm-auto-web-tester
Version: 0.1.4
Summary: Automated UI testing tool using Playwright MCP and OpenAI GPT agents.
Home-page: https://github.com/stefanini-applications/llm-auto-web-tester
Author: Lucas Custodio
Author-email: lucas.custodio@stefanini.com
Classifier: Programming Language :: Python :: 3.9
Classifier: Operating System :: OS Independent
Requires-Python: >=3.9
Requires-Dist: openai-agents
Requires-Dist: python-dotenv
Requires-Dist: openai
Requires-Dist: playwright
Requires-Dist: rich
Requires-Dist: requests
Requires-Dist: asyncio
Requires-Dist: playwright-mcp
Dynamic: author
Dynamic: author-email
Dynamic: classifier
Dynamic: description
Dynamic: description-content-type
Dynamic: home-page
Dynamic: requires-dist
Dynamic: requires-python
Dynamic: summary
